setup.py
djangocas/__init__.py
djangocas/backends.py
djangocas/decorators.py
djangocas/middleware.py
djangocas/views.py
djangocas.egg-info/PKG-INFO
djangocas.egg-info/SOURCES.txt
djangocas.egg-info/dependency_links.txt
djangocas.egg-info/requires.txt
djangocas.egg-info/top_level.txt