Metadata-Version: 1.0
Name: djangocas
Version: 1.0.0
Summary: CAS 1.0/2.0 authentication backend for Django
Home-page: https://github.com/mdj2/djangocas
Author: mdj2
Author-email: mdj2@pdx.edu
License: MIT
Platform: UNKNOWN
Classifier: Framework :: Django
Classifier: Programming Language :: Python :: 2
Classifier: Programming Language :: Python :: 3
